reddit_irc.py
reddit_irc-0.1.3.dist-info/entry_points.txt
reddit_irc-0.1.3.dist-info/RECORD
reddit_irc-0.1.3.dist-info/metadata.json
reddit_irc-0.1.3.dist-info/top_level.txt
reddit_irc-0.1.3.dist-info/WHEEL
reddit_irc-0.1.3.dist-info/DESCRIPTION.rst
reddit_irc-0.1.3.dist-info/METADATA
