Metadata-Version: 2.0
Name: reddit-irc
Version: 0.1.3
Summary: A tool to post new subreddit submissions to IRC channels.
Home-page: https://github.com/bboe/reddit_irc
Author: Bryce Boe
Author-email: bbzbryce@gmail.com
License: Simplified BSD License
Keywords: reddit submission irc notification
Platform: UNKNOWN
Classifier: License :: OSI Approved :: BSD License
Classifier: Operating System :: OS Independent
Classifier: Programming Language :: Python
Requires-Dist: ircutils
Requires-Dist: praw (>=2.0.11)
